rtl/src/tdnn_generator.v
//==============================================================================
// 6G PA GAN-DPD: TDNN Generator (Memory-Aware Neural Network)
//==============================================================================
//
// Description:
//   Time-Delay Neural Network generator for DPD.
//   Architecture: FC1(22→32) → LeakyReLU → FC2(32→16) → LeakyReLU → FC3(16→2) → Tanh
//
// Quantization:
//   Weights:     Q1.15 (16-bit signed)
//   Activations: Q8.8 (16-bit signed)
//   Accumulator: Q16.16 (32-bit)
//
// Timing:
//   - Pipelined MAC with 6 parallel multipliers
//   - Latency: ~50 cycles per sample at 200 MHz
//   - Throughput: 1 sample per ~50 cycles (4 Msps)
//
// Author: Generated for 6G PA GAN-DPD Project
//==============================================================================

`timescale 1ns / 1ps

module tdnn_generator #(
    parameter DATA_WIDTH    = 16,           // Q1.15 input/output
    parameter WEIGHT_WIDTH  = 16,           // Q1.15 weights
    parameter ACT_WIDTH     = 16,           // Q8.8 activations
    parameter ACC_WIDTH     = 32,           // Q16.16 accumulator
    parameter MEMORY_DEPTH  = 5,            // Memory taps
    parameter INPUT_DIM     = 2 + 2*MEMORY_DEPTH*2,  // 2 + 2*M*2 = 22 (matches Python)
    parameter HIDDEN1_DIM   = 32,
    parameter HIDDEN2_DIM   = 16,
    parameter OUTPUT_DIM    = 2,
    parameter NUM_MACS      = 6             // Parallel MAC units
)(
    input  wire                     clk,
    input  wire                     rst_n,
    
    // Input vector (memory-assembled)
    input  wire [DATA_WIDTH*INPUT_DIM-1:0] in_vector,
    input  wire                     in_valid,
    
    // Weight memory interface
    output reg  [15:0]              weight_addr,
    input  wire [WEIGHT_WIDTH-1:0]  weight_data,
    input  wire [1:0]               weight_bank_sel,
    
    // Output
    output reg  [DATA_WIDTH-1:0]    out_i,
    output reg  [DATA_WIDTH-1:0]    out_q,
    output reg                      out_valid,
    
    // Status
    output wire                     busy
);

    //==========================================================================
    // Local Parameters
    //==========================================================================
    
    // Weight address offsets (UPDATED for 22 inputs)
    localparam WADDR_FC1 = 0;                           // 22*32 = 704 weights
    localparam WADDR_B1  = 704;                         // 32 biases
    localparam WADDR_FC2 = 736;                         // 32*16 = 512 weights
    localparam WADDR_B2  = 1248;                        // 16 biases
    localparam WADDR_FC3 = 1264;                        // 16*2 = 32 weights
    localparam WADDR_B3  = 1296;                        // 2 biases
    
    // Bank offset (UPDATED total)
    localparam BANK_SIZE = 1298;  // Total parameters per temperature bank
    
    // State machine
    localparam ST_IDLE     = 4'd0;
    localparam ST_LOAD     = 4'd1;
    localparam ST_FC1      = 4'd2;
    localparam ST_ACT1     = 4'd3;
    localparam ST_FC2      = 4'd4;
    localparam ST_ACT2     = 4'd5;
    localparam ST_FC3      = 4'd6;
    localparam ST_TANH     = 4'd7;
    localparam ST_OUTPUT   = 4'd8;
    
    //==========================================================================
    // Internal Registers
    //==========================================================================
    
    reg [3:0] state, next_state;
    
    // Input buffer
    reg signed [DATA_WIDTH-1:0] input_buf [0:INPUT_DIM-1];
    
    // Layer outputs
    reg signed [ACT_WIDTH-1:0] fc1_out [0:HIDDEN1_DIM-1];
    reg signed [ACT_WIDTH-1:0] fc2_out [0:HIDDEN2_DIM-1];
    reg signed [DATA_WIDTH-1:0] fc3_out [0:OUTPUT_DIM-1];
    
    // Initialize layer outputs
    integer k;
    initial begin
        for (k = 0; k < HIDDEN1_DIM; k = k + 1) fc1_out[k] = 0;
        for (k = 0; k < HIDDEN2_DIM; k = k + 1) fc2_out[k] = 0;
        for (k = 0; k < OUTPUT_DIM; k = k + 1) fc3_out[k] = 0;
    end
    
    // MAC accumulator
    reg signed [ACC_WIDTH-1:0] acc [0:NUM_MACS-1];
    
    // Counters
    reg [5:0] in_idx;      // Input index
    reg [5:0] out_idx;     // Output index
    reg [5:0] mac_cnt;     // MAC counter
    
    // Weight bank base address
    wire [15:0] bank_base = weight_bank_sel * BANK_SIZE;
    
    // Initialize accumulators
    integer j;
    initial begin
        for (j = 0; j < NUM_MACS; j = j + 1) begin
            acc[j] = 0;
        end
    end
    
    //==========================================================================
    // State Machine
    //==========================================================================
    
    assign busy = (state != ST_IDLE);
    
    always @(posedge clk or negedge rst_n) begin
        if (!rst_n)
            state <= ST_IDLE;
        else
            state <= next_state;
    end
    
    always @(*) begin
        next_state = state;
        case (state)
            ST_IDLE:    if (in_valid) next_state = ST_LOAD;
            ST_LOAD:    next_state = ST_FC1;
            ST_FC1:     if (out_idx == HIDDEN1_DIM) next_state = ST_ACT1;
            ST_ACT1:    next_state = ST_FC2;
            ST_FC2:     if (out_idx == HIDDEN2_DIM) next_state = ST_ACT2;
            ST_ACT2:    next_state = ST_FC3;
            ST_FC3:     if (out_idx == OUTPUT_DIM) next_state = ST_TANH;
            ST_TANH:    next_state = ST_OUTPUT;
            ST_OUTPUT:  next_state = ST_IDLE;
            default:    next_state = ST_IDLE;
        endcase
    end
    
    //==========================================================================
    // Input Loading
    //==========================================================================
    
    integer i;
    always @(posedge clk) begin
        if (state == ST_LOAD || (state == ST_IDLE && in_valid)) begin
            for (i = 0; i < INPUT_DIM; i = i + 1) begin
                input_buf[i] <= in_vector[DATA_WIDTH*i +: DATA_WIDTH];
            end
        end
    end
    
    //==========================================================================
    // FC Layer Processing (Pipelined)
    //==========================================================================
    
    // Weight address generation
    always @(posedge clk) begin
        case (state)
            ST_FC1: weight_addr <= bank_base + WADDR_FC1 + out_idx * INPUT_DIM + in_idx;
            ST_FC2: weight_addr <= bank_base + WADDR_FC2 + out_idx * HIDDEN1_DIM + in_idx;
            ST_FC3: weight_addr <= bank_base + WADDR_FC3 + out_idx * HIDDEN2_DIM + in_idx;
            default: weight_addr <= 0;
        endcase
    end
    
    // MAC accumulator logic
    reg signed [DATA_WIDTH-1:0] mac_input;
    reg signed [WEIGHT_WIDTH-1:0] mac_weight;
    wire signed [2*DATA_WIDTH-1:0] mac_product = mac_input * mac_weight;
    
    always @(posedge clk or negedge rst_n) begin
        if (!rst_n) begin
            in_idx <= 0;
            out_idx <= 0;
            mac_cnt <= 0;
            for (i = 0; i < NUM_MACS; i = i + 1) begin
                acc[i] <= 0;
            end
        end
        else begin
            case (state)
                ST_IDLE: begin
                    in_idx <= 0;
                    out_idx <= 0;
                    mac_cnt <= 0;
                    acc[0] <= 0;  // Reset accumulator for next computation
                end
                
                ST_FC1: begin
                    // FC1: 22 inputs → 32 outputs
                    
                    // Fetch weight and input
                    mac_weight <= weight_data;
                    mac_input <= input_buf[in_idx];
                    
                    // Accumulate (starts from cycle 1)
                    if (in_idx > 0 || mac_cnt > 0) begin
                        acc[0] <= acc[0] + mac_product;
                    end
                    
                    // Move to next input
                    if (in_idx == INPUT_DIM - 1) begin
                        // Finished one neuron - store result
                        fc1_out[out_idx] <= (acc[0] + mac_product) >>> 16;  // Q16.16 -> Q8.8
                        out_idx <= out_idx + 1;
                        in_idx <= 0;
                        acc[0] <= 0;  // Reset for next neuron
                    end
                    else begin
                        in_idx <= in_idx + 1;
                    end
                    mac_cnt <= mac_cnt + 1;
                end
                
                ST_FC2: begin
                    // FC2: 32 inputs → 16 outputs
                    
                    mac_weight <= weight_data;
                    mac_input <= fc1_out[in_idx];
                    
                    if (in_idx > 0 || mac_cnt > 0) begin
                        acc[0] <= acc[0] + mac_product;
                    end
                    
                    if (in_idx == HIDDEN1_DIM - 1) begin
                        fc2_out[out_idx] <= (acc[0] + mac_product) >>> 16;  // Q16.16 -> Q8.8
                        out_idx <= out_idx + 1;
                        in_idx <= 0;
                        acc[0] <= 0;
                    end
                    else begin
                        in_idx <= in_idx + 1;
                    end
                    mac_cnt <= mac_cnt + 1;
                end
                
                ST_FC3: begin
                    // FC3: 16 inputs → 2 outputs
                    
                    mac_weight <= weight_data;
                    mac_input <= fc2_out[in_idx];
                    
                    if (in_idx > 0 || mac_cnt > 0) begin
                        acc[0] <= acc[0] + mac_product;
                    end
                    
                    if (in_idx == HIDDEN2_DIM - 1) begin
                        fc3_out[out_idx] <= (acc[0] + mac_product) >>> 16;  // Q16.16 -> Q1.15
                        out_idx <= out_idx + 1;
                        in_idx <= 0;
                        acc[0] <= 0;
                    end
                    else begin
                        in_idx <= in_idx + 1;
                    end
                    mac_cnt <= mac_cnt + 1;
                end
                
                ST_ACT1: begin
                    out_idx <= 0;
                    in_idx <= 0;
                    mac_cnt <= 0;
                end
                
                ST_ACT2: begin
                    out_idx <= 0;
                    in_idx <= 0;
                    mac_cnt <= 0;
                end
            endcase
        end
    end
    
    //==========================================================================
    // LeakyReLU Activation (α = 0.25 ≈ 1/4, implemented as >>2)
    //==========================================================================
    
    always @(posedge clk) begin
        if (state == ST_ACT1) begin
            for (i = 0; i < HIDDEN1_DIM; i = i + 1) begin
                if (fc1_out[i] < 0)
                    fc1_out[i] <= fc1_out[i] >>> 2;  // x * 0.25
                // else keep positive values unchanged
            end
        end
        
        if (state == ST_ACT2) begin
            for (i = 0; i < HIDDEN2_DIM; i = i + 1) begin
                if (fc2_out[i] < 0)
                    fc2_out[i] <= fc2_out[i] >>> 2;
            end
        end
    end
    
    //==========================================================================
    // Tanh Activation (LUT-based)
    //==========================================================================
    
    // Tanh LUT (256 entries, Q1.15 output)
    // Input range: [-4, 4] mapped to [0, 255]
    reg signed [DATA_WIDTH-1:0] tanh_lut [0:255];
    
    // Initialize LUT from hex file
    initial begin
        $display("Loading tanh LUT from tanh_lut.hex");
        $readmemh("tanh_lut.hex", tanh_lut);
        $display("Tanh LUT loaded: first=0x%h, mid=0x%h, last=0x%h", 
                 tanh_lut[0], tanh_lut[128], tanh_lut[255]);
    end
    
    // LUT index calculation
    wire [7:0] tanh_idx_i = (fc3_out[0] + 16'sh8000) >> 8;  // Map to [0, 255]
    wire [7:0] tanh_idx_q = (fc3_out[1] + 16'sh8000) >> 8;
    
    always @(posedge clk) begin
        if (state == ST_TANH) begin
            // Apply tanh via LUT
            fc3_out[0] <= tanh_lut[tanh_idx_i];
            fc3_out[1] <= tanh_lut[tanh_idx_q];
        end
    end
    
    //==========================================================================
    // Output Stage
    //==========================================================================
    
    always @(posedge clk or negedge rst_n) begin
        if (!rst_n) begin
            out_i <= 0;
            out_q <= 0;
            out_valid <= 0;
        end
        else begin
            out_valid <= 0;
            
            if (state == ST_OUTPUT) begin
                out_i <= fc3_out[0];
                out_q <= fc3_out[1];
                out_valid <= 1;
            end
        end
    end

endmodule

rtl/tb/tb_tdnn_simple.v
`timescale 1ns/1ps

module tb_tdnn_simple;
    parameter DATA_WIDTH = 16;
    parameter INPUT_DIM = 22;  // UPDATED: 2 + 2*5*2 = 22 features
    
    reg clk, rst_n;
    reg [DATA_WIDTH*INPUT_DIM-1:0] in_vector;
    reg in_valid;
    wire signed [DATA_WIDTH-1:0] out_i, out_q;
    wire out_valid, busy;
    
    wire [15:0] weight_addr;
    reg signed [15:0] weight_data;
    reg [1:0] weight_bank_sel;
    
    // Weight memory (1298 params per bank × 3 banks = 3894 total)
    reg signed [15:0] weight_mem [0:3999];
    
    initial begin
        integer i;
        // Initialize with test values (extended for 22 inputs)
        for (i = 0; i < 4000; i = i + 1) begin
            weight_mem[i] = 16'h1000;  // 0.125 in Q1.15 (4096/32768)
        end
        $display("Initialized %0d weights to 0x1000 (0.125 in Q1.15)", 4000);
    end
    
    always @(posedge clk) begin
        weight_data <= weight_mem[weight_addr];
    end
    
    // DUT
    tdnn_generator dut (
        .clk(clk),
        .rst_n(rst_n),
        .in_vector(in_vector),
        .in_valid(in_valid),
        .weight_addr(weight_addr),
        .weight_data(weight_data),
        .weight_bank_sel(weight_bank_sel),
        .out_i(out_i),
        .out_q(out_q),
        .out_valid(out_valid),
        .busy(busy)
    );
    
    // Clock
    initial begin
        clk = 0;
        forever #2.5 clk = ~clk;  // 200MHz
    end
    
    // Test
    integer i, timeout_cnt;
    
    initial begin
        $dumpfile("tb_tdnn_simple.vcd");
        $dumpvars(0, tb_tdnn_simple);
        
        rst_n = 0;
        in_valid = 0;
        in_vector = 0;
        weight_bank_sel = 0;
        
        #100;
        rst_n = 1;
        #50;
        
        // Test with simple input
        $display("=== Starting Simple TDNN Test (22 inputs) ===");
        $display("Input: Setting I=0.5, Q=0.25, rest=0.1");
        
        in_vector[0*16 +: 16] = 16'h4000;  // I = 0.5
        in_vector[1*16 +: 16] = 16'h2000;  // Q = 0.25
        
        for (i = 2; i < 22; i = i + 1) begin
            in_vector[i*16 +: 16] = 16'h0CCC;  // 0.1
        end
        
        @(posedge clk);
        in_valid <= 1;
        $display("[%0t] Input valid asserted", $time);
        
        @(posedge clk);
        in_valid <= 0;
        $display("[%0t] Input valid deasserted", $time);
        
        // Wait for out_valid with timeout
        timeout_cnt = 0;
        while (!out_valid && timeout_cnt < 20000) begin
            @(posedge clk);
            timeout_cnt = timeout_cnt + 1;
        end
        
        if (timeout_cnt >= 20000) begin
            $display("[%0t] ✗ TIMEOUT waiting for out_valid", $time);
            $display("  Current state: %0d", dut.state);
            $display("  out_idx: %0d, in_idx: %0d, mac_cnt: %0d", dut.out_idx, dut.in_idx, dut.mac_cnt);
            $display("  busy: %0d", busy);
            $finish;
        end
        
        // Capture outputs when out_valid is high
        $display("[%0t] ✓ out_valid asserted after %0d cycles", $time, timeout_cnt);
        $display("  out_i = %d (0x%h) = %f", out_i, out_i, $itor(out_i)/32768.0);
        $display("  out_q = %d (0x%h) = %f", out_q, out_q, $itor(out_q)/32768.0);
        
        // Capture outputs when out_valid is high
        $display("[%0t] ✓ out_valid asserted after %0d cycles", $time, timeout_cnt);
        $display("  out_i = %d (0x%h) = %f", out_i, out_i, $itor(out_i)/32768.0);
        $display("  out_q = %d (0x%h) = %f", out_q, out_q, $itor(out_q)/32768.0);
        
        #100;
        
        if (out_i == 0 && out_q == 0) begin
            $display("\n✗ FAIL: Outputs are zero (weights not being applied)");
            $display("   This usually means:");
            $display("   1. Weight memory reads are returning 0");
            $display("   2. MAC accumulation is not working");
            $display("   3. Pipeline timing is incorrect");
        end else begin
            $display("\n✓ PASS: Non-zero output detected!");
            $display("   TDNN inference is working correctly");
        end
        
        #200;
        $display("=== Test Complete ===");
        $finish;
    end
    
    // Monitor state changes with more detail
    always @(dut.state) begin
        case (dut.state)
            0: $display("[%0t] STATE: IDLE", $time);
            1: $display("[%0t] STATE: LOAD", $time);
            2: $display("[%0t] STATE: FC1 (will compute 32 neurons of 22 weights each = 704 total)", $time);
            3: $display("[%0t] STATE: ACT1 (out_idx=%0d, should be 32)", $time, dut.out_idx);
            4: $display("[%0t] STATE: FC2 (will compute 16 neurons of 32 weights each = 512 total)", $time);
            5: $display("[%0t] STATE: ACT2 (out_idx=%0d, should be 16)", $time, dut.out_idx);
            6: $display("[%0t] STATE: FC3 (will compute 2 neurons of 16 weights each = 32 total)", $time);
            7: $display("[%0t] STATE: TANH (out_idx=%0d, should be 2)", $time, dut.out_idx);
            8: $display("[%0t] STATE: OUTPUT", $time);
        endcase
    end
    
    // Monitor neuron completion in FC1 with accumulator values
    always @(posedge clk) begin
        if (dut.state == 2 && dut.in_idx == 21 && dut.out_idx < 3) begin  // FC1, last input of first 3 neurons (22-1=21)
            $display("[%0t] FC1: Completed neuron %0d - acc[0]=0x%08h (%0d decimal)", 
                     $time, dut.out_idx, dut.acc[0], $signed(dut.acc[0]));
        end
        if (dut.state == 2 && dut.in_idx == 0 && dut.out_idx < 3 && dut.mac_cnt > 0) begin
            $display("[%0t] FC1: Starting neuron %0d - acc[0]=0x%08h (should be 0)", 
                     $time, dut.out_idx, dut.acc[0]);
        end
    end
    
    // Monitor MAC operations for first neuron
    reg monitor_mac;
    initial monitor_mac = 1;
    
    always @(posedge clk) begin
        if (monitor_mac && dut.state == 2 && dut.out_idx == 0 && dut.in_idx < 5) begin
            $display("[%0t] MAC[neuron=0, input=%0d]: weight=0x%04h, input=0x%04h, product=0x%08h, acc=0x%08h",
                     $time, dut.in_idx, dut.mac_weight, dut.mac_input, 
                     dut.mac_product, dut.acc[0]);
        end
        if (dut.state == 2 && dut.out_idx == 1) begin
            monitor_mac = 0;  // Stop monitoring after first neuron
        end
    end
    
    // Monitor weight reads (limit to first few to avoid spam)
    reg [15:0] last_weight_addr;
    integer weight_read_count;
    
    initial begin
        weight_read_count = 0;
        last_weight_addr = 16'hFFFF;
    end
    
    always @(posedge clk) begin
        if (weight_addr != last_weight_addr && weight_read_count < 30) begin
            $display("[%0t] Weight[%4d] = 0x%04h (busy=%0d, state=%0d)", 
                     $time, weight_addr, weight_data, busy, dut.state);
            last_weight_addr = weight_addr;
            weight_read_count = weight_read_count + 1;
        end
    end
    
    // Timeout
    initial begin
        #100000;
        $display("✗ TIMEOUT");
        $finish;
    end
    
endmodule

rtl/wave/tb_tdnn_simple.vcd
$date
	Thu Jan  1 23:58:23 2026
$end
$version
	Icarus Verilog
$end
$timescale
	1ps
$end
$scope module tb_tdnn_simple $end
$var wire 16 ! weight_addr [15:0] $end
$var wire 1 " out_valid $end
$var wire 16 # out_q [15:0] $end
$var wire 16 $ out_i [15:0] $end
$var wire 1 % busy $end
$var parameter 32 & DATA_WIDTH $end
$var parameter 32 ' INPUT_DIM $end
$var reg 1 ( clk $end
$var reg 1 ) in_valid $end
$var reg 352 * in_vector [351:0] $end
$var reg 16 + last_weight_addr [15:0] $end
$var reg 1 , monitor_mac $end
$var reg 1 - rst_n $end
$var reg 2 . weight_bank_sel [1:0] $end
$var reg 16 / weight_data [15:0] $end
$var integer 32 0 i [31:0] $end
$var integer 32 1 timeout_cnt [31:0] $end
$var integer 32 2 weight_read_count [31:0] $end
$scope module dut $end
$var wire 1 ( clk $end
$var wire 1 ) in_valid $end
$var wire 352 3 in_vector [351:0] $end
$var wire 1 - rst_n $end
$var wire 2 4 weight_bank_sel [1:0] $end
$var wire 16 5 weight_data [15:0] $end
$var wire 8 6 tanh_idx_q [7:0] $end
$var wire 8 7 tanh_idx_i [7:0] $end
$var wire 32 8 mac_product [31:0] $end
$var wire 1 % busy $end
$var wire 16 9 bank_base [15:0] $end
$var parameter 32 : ACC_WIDTH $end
$var parameter 32 ; ACT_WIDTH $end
$var parameter 32 < BANK_SIZE $end
$var parameter 32 = DATA_WIDTH $end
$var parameter 32 > HIDDEN1_DIM $end
$var parameter 32 ? HIDDEN2_DIM $end
$var parameter 97 @ INPUT_DIM $end
$var parameter 32 A MEMORY_DEPTH $end
$var parameter 32 B NUM_MACS $end
$var parameter 32 C OUTPUT_DIM $end
$var parameter 4 D ST_ACT1 $end
$var parameter 4 E ST_ACT2 $end
$var parameter 4 F ST_FC1 $end
$var parameter 4 G ST_FC2 $end
$var parameter 4 H ST_FC3 $end
$var parameter 4 I ST_IDLE $end
$var parameter 4 J ST_LOAD $end
$var parameter 4 K ST_OUTPUT $end
$var parameter 4 L ST_TANH $end
$var parameter 32 M WADDR_B1 $end
$var parameter 32 N WADDR_B2 $end
$var parameter 32 O WADDR_B3 $end
$var parameter 32 P WADDR_FC1 $end
$var parameter 32 Q WADDR_FC2 $end
$var parameter 32 R WADDR_FC3 $end
$var parameter 32 S WEIGHT_WIDTH $end
$var reg 6 T in_idx [5:0] $end
$var reg 6 U mac_cnt [5:0] $end
$var reg 16 V mac_input [15:0] $end
$var reg 16 W mac_weight [15:0] $end
$var reg 4 X next_state [3:0] $end
$var reg 16 Y out_i [15:0] $end
$var reg 6 Z out_idx [5:0] $end
$var reg 16 [ out_q [15:0] $end
$var reg 1 " out_valid $end
$var reg 4 \ state [3:0] $end
$var reg 16 ] weight_addr [15:0] $end
$var integer 32 ^ i [31:0] $end
$var integer 32 _ j [31:0] $end
$var integer 32 ` k [31:0] $end
$upscope $end
$scope begin $unm_blk_56 $end
$var integer 32 a i [31:0] $end
$upscope $end
$upscope $end
$enddefinitions $end
$comment Show the parameter values. $end
$dumpall
b10000 S
b10011110000 R
b1011100000 Q
b0 P
b10100010000 O
b10011100000 N
b1011000000 M
b111 L
b1000 K
b1 J
b0 I
b110 H
b100 G
b10 F
b101 E
b11 D
b10 C
b110 B
b101 A
b10110 @
b10000 ?
b100000 >
b10000 =
b10100010010 <
b10000 ;
b100000 :
b10110 '
b10000 &
$end
#0
$dumpvars
b111110100000 a
b10 `
b110 _
b110 ^
bx ]
b0 \
b0 [
b0 Z
b0 Y
b0 X
bx W
bx V
b0 U
b0 T
b0 9
bx 8
b10000000 7
b10000000 6
bx 5
b0 4
b0 3
b0 2
bx 1
bx 0
bx /
b0 .
0-
1,
b1111111111111111 +
b0 *
0)
0(
0%
b0 $
b0 #
0"
bx !
$end
#2500
b0 !
b0 ]
b110 ^
1(
#5000
0(
#7500
b1000000000000 /
b1000000000000 5
b110 ^
b1 2
b0 +
1(
#10000
0(
#12500
b110 ^
1(
#15000
0(
#17500
b110 ^
1(
#20000
0(
#22500
b110 ^
1(
#25000
0(
#27500
b110 ^
1(
#30000
0(
#32500
b110 ^
1(
#35000
0(
#37500
b110 ^
1(
#40000
0(
#42500
b110 ^
1(
#45000
0(
#47500
b110 ^
1(
#50000
0(
#52500
b110 ^
1(
#55000
0(
#57500
b110 ^
1(
#60000
0(
#62500
b110 ^
1(
#65000
0(
#67500
b110 ^
1(
#70000
0(
#72500
b110 ^
1(
#75000
0(
#77500
b110 ^
1(
#80000
0(
#82500
b110 ^
1(
#85000
0(
#87500
b110 ^
1(
#90000
0(
#92500
b110 ^
1(
#95000
0(
#97500
b110 ^
1(
#100000
0(
1-
#102500
1(
#105000
0(
#107500
1(
#110000
0(
#112500
1(
#115000
0(
#117500
1(
#120000
0(
#122500
1(
#125000
0(
#127500
1(
#130000
0(
#132500
1(
#135000
0(
#137500
1(
#140000
0(
#142500
1(
#145000
0(
#147500
1(
#150000
0(
b10110 0
b110011001100000011001100110000001100110011000000110011001100000011001100110000001100110011000000110011001100000011001100110000001100110011000000110011001100000011001100110000001100110011000000110011001100000011001100110000001100110011000000110011001100000011001100110000001100110011000000110011001100000011001100110000100000000000000100000000000000 *
b110011001100000011001100110000001100110011000000110011001100000011001100110000001100110011000000110011001100000011001100110000001100110011000000110011001100000011001100110000001100110011000000110011001100000011001100110000001100110011000000110011001100000011001100110000001100110011000000110011001100000011001100110000100000000000000100000000000000 3
#152500
b1 X
1)
1(
#155000
0(
#157500
b10 X
1%
b1 \
0)
b0 1
b10110 ^
1(
#160000
0(
#162500
b10 \
b10110 ^
b1 1
1(
#165000
0(
#167500
b1 U
b1 T
b100000000000000000000000000 8
b100000000000000 V
b1000000000000 W
b10 1
1(
#170000
0(
#172500
b10 U
b10 T
b10000000000000000000000000 8
b10000000000000 V
b1 !
b1 ]
b11 1
1(
#175000
0(
#177500
b11 U
b11 T
b110011001100000000000000 8
b110011001100 V
b10 !
b10 ]
b100 1
b10 2
b1 +
1(
#180000
0(
#182500
b100 U
b100 T
b11 !
b11 ]
b11 2
b10 +
b101 1
1(
#185000
0(
#187500
b101 U
b101 T
b100 !
b100 ]
b110 1
b100 2
b11 +
1(
#190000
0(
#192500
b110 U
b110 T
b101 !
b101 ]
b101 2
b100 +
b111 1
1(
#195000
0(
#197500
b111 U
b111 T
b110 !
b110 ]
b1000 1
b110 2
b101 +
1(
#200000
0(
#202500
b1000 U
b1000 T
b111 !
b111 ]
b111 2
b110 +
b1001 1
1(
#205000
0(
#207500
b1001 U
b1001 T
b1000 !
b1000 ]
b1010 1
b1000 2
b111 +
1(
#210000
0(
#212500
b1010 U
b1010 T
b1001 !
b1001 ]
b1001 2
b1000 +
b1011 1
1(
#215000
0(
#217500
b1011 U
b1011 T
b1010 !
b1010 ]
b1100 1
b1010 2
b1001 +
1(
#220000
0(
#222500
b1100 U
b1100 T
b1011 !
b1011 ]
b1011 2
b1010 +
b1101 1
1(
#225000
0(
#227500
b1101 U
b1101 T
b1100 !
b1100 ]
b1110 1
b1100 2
b1011 +
1(
#230000
0(
#232500
b1110 U
b1110 T
b1101 !
b1101 ]
b1101 2
b1100 +
b1111 1
1(
#235000
0(
#237500
b1111 U
b1111 T
b1110 !
b1110 ]
b10000 1
b1110 2
b1101 +
1(
#240000
0(
#242500
b10000 U
b10000 T
b1111 !
b1111 ]
b1111 2
b1110 +
b10001 1
1(
#245000
0(
#247500
b10001 U
b10001 T
b10000 !
b10000 ]
b10010 1
b10000 2
b1111 +
1(
#250000
0(
#252500
b10010 U
b10010 T
b10001 !
b10001 ]
b10001 2
b10000 +
b10011 1
1(
#255000
0(
#257500
b10011 U
b10011 T
b10010 !
b10010 ]
b10100 1
b10010 2
b10001 +
1(
#260000
0(
#262500
b10100 U
b10100 T
b10011 !
b10011 ]
b10011 2
b10010 +
b10101 1
1(
#265000
0(
#267500
b10101 U
b10101 T
b10100 !
b10100 ]
b10110 1
b10100 2
b10011 +
1(
#270000
0(
#272500
b10110 U
b0 T
b1 Z
b10101 !
b10101 ]
b10101 2
b10100 +
b10111 1
1(
#275000
0(
#277500
b10111 U
b1 T
b100000000000000000000000000 8
b100000000000000 V
b10110 !
b10110 ]
b11000 1
b10110 2
b10101 +
0,
1(
#280000
0(
#282500
b11000 U
b10 T
b10000000000000000000000000 8
b10000000000000 V
b10111 !
b10111 ]
b10111 2
b10110 +
b11001 1
1(
#285000
0(
#287500
b11001 U
b11 T
b110011001100000000000000 8
b110011001100 V
b11000 !
b11000 ]
b11010 1
b11000 2
b10111 +
1(
#290000
0(
#292500
b11010 U
b100 T
b11001 !
b11001 ]
b11001 2
b11000 +
b11011 1
1(
#295000
0(
#297500
b11011 U
b101 T
b11010 !
b11010 ]
b11100 1
b11010 2
b11001 +
1(
#300000
0(
#302500
b11100 U
b110 T
b11011 !
b11011 ]
b11011 2
b11010 +
b11101 1
1(
#305000
0(
#307500
b11101 U
b111 T
b11100 !
b11100 ]
b11110 1
b11100 2
b11011 +
1(
#310000
0(
#312500
b11110 U
b1000 T
b11101 !
b11101 ]
b11101 2
b11100 +
b11111 1
1(
#315000
0(
#317500
b11111 U
b1001 T
b11110 !
b11110 ]
b100000 1
b11110 2
b11101 +
1(
#320000
0(
#322500
b100000 U
b1010 T
b11111 !
b11111 ]
b100001 1
1(
#325000
0(
#327500
b100001 U
b1011 T
b100000 !
b100000 ]
b100010 1
1(
#330000
0(
#332500
b100010 U
b1100 T
b100001 !
b100001 ]
b100011 1
1(
#335000
0(
#337500
b100011 U
b1101 T
b100010 !
b100010 ]
b100100 1
1(
#340000
0(
#342500
b100100 U
b1110 T
b100011 !
b100011 ]
b100101 1
1(
#345000
0(
#347500
b100101 U
b1111 T
b100100 !
b100100 ]
b100110 1
1(
#350000
0(
#352500
b100110 U
b10000 T
b100101 !
b100101 ]
b100111 1
1(
#355000
0(
#357500
b100111 U
b10001 T
b100110 !
b100110 ]
b101000 1
1(
#360000
0(
#362500
b101000 U
b10010 T
b100111 !
b100111 ]
b101001 1
1(
#365000
0(
#367500
b101001 U
b10011 T
b101000 !
b101000 ]
b101010 1
1(
#370000
0(
#372500
b101010 U
b10100 T
b101001 !
b101001 ]
b101011 1
1(
#375000
0(
#377500
b101011 U
b10101 T
b101010 !
b101010 ]
b101100 1
1(
#380000
0(
#382500
b101100 U
b0 T
b10 Z
b101011 !
b101011 ]
b101101 1
1(
#385000
0(
#387500
b101101 U
b1 T
b100000000000000000000000000 8
b100000000000000 V
b101100 !
b101100 ]
b101110 1
1(
#390000
0(
#392500
b101110 U
b10 T
b10000000000000000000000000 8
b10000000000000 V
b101101 !
b101101 ]
b101111 1
1(
#395000
0(
#397500
b101111 U
b11 T
b110011001100000000000000 8
b110011001100 V
b101110 !
b101110 ]
b110000 1
1(
#400000
0(
#402500
b110000 U
b100 T
b101111 !
b101111 ]
b110001 1
1(
#405000
0(
#407500
b110001 U
b101 T
b110000 !
b110000 ]
b110010 1
1(
#410000
0(
#412500
b110010 U
b110 T
b110001 !
b110001 ]
b110011 1
1(
#415000
0(
#417500
b110011 U
b111 T
b110010 !
b110010 ]
b110100 1
1(
#420000
0(
#422500
b110100 U
b1000 T
b110011 !
b110011 ]
b110101 1
1(
#425000
0(
#427500
b110101 U
b1001 T
b110100 !
b110100 ]
b110110 1
1(
#430000
0(
#432500
b110110 U
b1010 T
b110101 !
b110101 ]
b110111 1
1(
#435000
0(
#437500
b110111 U
b1011 T
b110110 !
b110110 ]
b111000 1
1(
#440000
0(
#442500
b111000 U
b1100 T
b110111 !
b110111 ]
b111001 1
1(
#445000
0(
#447500
b111001 U
b1101 T
b111000 !
b111000 ]
b111010 1
1(
#450000
0(
#452500
b111010 U
b1110 T
b111001 !
b111001 ]
b111011 1
1(
#455000
0(
#457500
b111011 U
b1111 T
b111010 !
b111010 ]
b111100 1
1(
#460000
0(
#462500
b111100 U
b10000 T
b111011 !
b111011 ]
b111101 1
1(
#465000
0(
#467500
b111101 U
b10001 T
b111100 !
b111100 ]
b111110 1
1(
#470000
0(
#472500
b111110 U
b10010 T
b111101 !
b111101 ]
b111111 1
1(
#475000
0(
#477500
b111111 U
b10011 T
b111110 !
b111110 ]
b1000000 1
1(
#480000
0(
#482500
b0 U
b10100 T
b111111 !
b111111 ]
b1000001 1
1(
#485000
0(
#487500
b1 U
b10101 T
b1000000 !
b1000000 ]
b1000010 1
1(
#490000
0(
#492500
b10 U
b0 T
b11 Z
b1000001 !
b1000001 ]
b1000011 1
1(
#495000
0(
#497500
b11 U
b1 T
b100000000000000000000000000 8
b100000000000000 V
b1000010 !
b1000010 ]
b1000100 1
1(
#500000
0(
#502500
b100 U
b10 T
b10000000000000000000000000 8
b10000000000000 V
b1000011 !
b1000011 ]
b1000101 1
1(
#505000
0(
#507500
b101 U
b11 T
b110011001100000000000000 8
b110011001100 V
b1000100 !
b1000100 ]
b1000110 1
1(
#510000
0(
#512500
b110 U
b100 T
b1000101 !
b1000101 ]
b1000111 1
1(
#515000
0(
#517500
b111 U
b101 T
b1000110 !
b1000110 ]
b1001000 1
1(
#520000
0(
